orbix/__init__.py
orbix/_version.py
orbix/constants.py
orbix/equations/__init__.py
orbix/equations/orbit.py
orbix/equations/phase.py
orbix/equations/propagation.py
orbix/fitting/core.py
orbix/integrations/__init__.py
orbix/integrations/exosims/__init__.py
orbix/integrations/exosims/_availability.py
orbix/integrations/exosims/dMag0.py
orbix/kepler/core.py
orbix/kepler/factories.py
orbix/kepler/shortcuts/__init__.py
orbix/kepler/shortcuts/fixed_e.py
orbix/kepler/shortcuts/grid.py
orbix/kepler/shortcuts/guess.py
orbix/predict/__init__.py
orbix/predict/pdet.py
orbix/system/__init__.py
orbix/system/planets.py
orbix/system/star.py
orbix/system/system.py
orbix-0.3.0.dist-info/METADATA
orbix-0.3.0.dist-info/WHEEL
orbix-0.3.0.dist-info/licenses/LICENSE
orbix-0.3.0.dist-info/RECORD
