Metadata-Version: 2.4
Name: orbix
Version: 0.3.0
Summary: A JAX library of functions useful for exoplanet simulations
Project-URL: Homepage, https://github.com/CoreySpohn/orbix
Project-URL: Issues, https://github.com/CoreySpohn/orbix/issues
License: MIT License
License-File: LICENSE
Requires-Python: >=3.10
Requires-Dist: equinox>=0.12.1
Requires-Dist: jax>=0.4.34
Requires-Dist: numpy>=2.1.2
Provides-Extra: docs
Requires-Dist: matplotlib; extra == 'docs'
Requires-Dist: myst-nb; extra == 'docs'
Requires-Dist: sphinx; extra == 'docs'
Requires-Dist: sphinx-autoapi; extra == 'docs'
Requires-Dist: sphinx-autodoc-typehints; extra == 'docs'
Requires-Dist: sphinx-book-theme; extra == 'docs'
Provides-Extra: exosims
Requires-Dist: exosims>=3.4.1; extra == 'exosims'
